cognitoauthenticator/__init__.py
cognitoauthenticator/apihandlers.py
cognitoauthenticator/cognitoauthenticator.py
cognitoauthenticator/common-credentials.txt
cognitoauthenticator/handlers.py
cognitoauthenticator/orm.py
cognitoauthenticator/crypto/__init__.py
cognitoauthenticator/crypto/crypto.py
cognitoauthenticator/crypto/encoding.py
cognitoauthenticator/crypto/signing.py
cognitoauthenticator/static/favicon.ico
cognitoauthenticator/static/images/jijzept_icon.png
cognitoauthenticator/static/images/jupyter.png
cognitoauthenticator/static/images/jupyterhub-80.png
cognitoauthenticator/static/images/sigma.png
cognitoauthenticator/static/images/sigma.svg
cognitoauthenticator/static/less/admin.less
cognitoauthenticator/static/less/error.less
cognitoauthenticator/static/less/login.less
cognitoauthenticator/static/less/page.less
cognitoauthenticator/static/less/style.less
cognitoauthenticator/static/less/variables.less
cognitoauthenticator/templates/404.html
cognitoauthenticator/templates/admin.html
cognitoauthenticator/templates/authorization-area.html
cognitoauthenticator/templates/change-password-admin.html
cognitoauthenticator/templates/change-password.html
cognitoauthenticator/templates/error.html
cognitoauthenticator/templates/home.html
cognitoauthenticator/templates/my_message.html
cognitoauthenticator/templates/native-login.html
cognitoauthenticator/templates/not_running.html
cognitoauthenticator/templates/oauth.html
cognitoauthenticator/templates/page.html
cognitoauthenticator/templates/signup.html
cognitoauthenticator/templates/spawn.html
cognitoauthenticator/templates/spawn_pending.html
cognitoauthenticator/templates/stop_pending.html
cognitoauthenticator/templates/token.html
cognitoauthenticator/tests/__init__.py
cognitoauthenticator/tests/test_authenticator.py
cognitoauthenticator/tests/test_orm.py
jijzeptlab_cognitoauthenticator-1.0.7.dist-info/LICENSE
jijzeptlab_cognitoauthenticator-1.0.7.dist-info/METADATA
jijzeptlab_cognitoauthenticator-1.0.7.dist-info/WHEEL
jijzeptlab_cognitoauthenticator-1.0.7.dist-info/top_level.txt
jijzeptlab_cognitoauthenticator-1.0.7.dist-info/RECORD
